thamos/__init__.py
thamos/cli.py
thamos/cli_config.py
thamos/config.py
thamos/discover.py
thamos/exceptions.py
thamos/lib.py
thamos/py.typed
thamos/utils.py
thamos/data/defaultThoth.yaml
thamos/swagger_client/__init__.py
thamos/swagger_client/api_client.py
thamos/swagger_client/configuration.py
thamos/swagger_client/rest.py
thamos/swagger_client/models/__init__.py
thamos/swagger_client/models/advise_input.py
thamos/swagger_client/models/advise_input_library_usage.py
thamos/swagger_client/models/adviser_result_response.py
thamos/swagger_client/models/adviser_result_response_metadata.py
thamos/swagger_client/models/adviser_result_response_metadata_distribution.py
thamos/swagger_client/models/adviser_result_response_metadata_distribution_version_parts.py
thamos/swagger_client/models/adviser_result_response_metadata_python.py
thamos/swagger_client/models/adviser_result_response_result.py
thamos/swagger_client/models/adviser_result_response_result_report.py
thamos/swagger_client/models/adviser_result_response_result_report_dependency_graph.py
thamos/swagger_client/models/adviser_result_response_result_report_pipeline.py
thamos/swagger_client/models/adviser_result_response_result_report_products.py
thamos/swagger_client/models/analysis_log_response.py
thamos/swagger_client/models/analysis_response.py
thamos/swagger_client/models/analysis_response_error.py
thamos/swagger_client/models/analysis_result_response.py
thamos/swagger_client/models/analysis_result_response_metadata.py
thamos/swagger_client/models/analysis_result_response_result.py
thamos/swagger_client/models/analysis_result_response_result_aicoeci.py
thamos/swagger_client/models/analysis_result_response_result_deb.py
thamos/swagger_client/models/analysis_result_response_result_debdependencies.py
thamos/swagger_client/models/analysis_result_response_result_pythonfiles.py
thamos/swagger_client/models/analysis_result_response_result_pythoninterpreters.py
thamos-1.29.1.dist-info/LICENSE
thamos-1.29.1.dist-info/METADATA
thamos-1.29.1.dist-info/WHEEL
thamos-1.29.1.dist-info/entry_points.txt
thamos-1.29.1.dist-info/top_level.txt
thamos-1.29.1.dist-info/RECORD
