Metadata-Version: 2.1
Name: thamos
Version: 1.29.1
Summary: A CLI tool and library for interacting with Thoth
Home-page: https://github.com/thoth-station/thamos
Author: Fridolin Pokorny
Author-email: fridolin@redhat.com
License: GPLv3+
Project-URL: Documentation, https://thoth-station.ninja/docs/developers/thamos/index.html
Project-URL: Source Code, https://github.com/thoth-station/thamos/
Project-URL: Issues, https://github.com/thoth-station/thamos/issues
Project-URL: CI, https://prow.operate-first.cloud/?repo=thoth-station%2Fthamos
Project-URL: Changelog, https://github.com/thoth-station/thamos/blob/master/CHANGELOG.md
License-File: LICENSE
